gyakujinton/Shape/Shape.py
gyakujinton/Shape/__init__.py
gyakujinton/Window/Window.py
gyakujinton/Window/__init__.py
gyakujinton/__init__.py
gyakujinton/cli.py
gyakujinton/functions/draw.py
gyakujinton/functions/rotate.py
gyakujinton/functions/skew.py
gyakujinton-0.4.0.dist-info/entry_points.txt
gyakujinton-0.4.0.dist-info/LICENSE
gyakujinton-0.4.0.dist-info/WHEEL
gyakujinton-0.4.0.dist-info/METADATA
gyakujinton-0.4.0.dist-info/RECORD
