Metadata-Version: 2.1
Name: gyakujinton
Version: 0.4.0
Summary: 
Home-page: https://github.com/mamerisawesome/gyakujinton
License: MIT
Author: Almer Mendoza
Author-email: atmalmer23@gmail.com
Requires-Python: >=3.6.1,<4.0.0
Classifier: License :: OSI Approved :: MIT License
Classifier: Programming Language :: Python :: 3
Classifier: Programming Language :: Python :: 3.7
Classifier: Programming Language :: Python :: 3.8
Requires-Dist: matplotlib (>=3.2.1,<4.0.0)
Requires-Dist: numpy (>=1.18.2,<2.0.0)
Requires-Dist: pandas (>=1.0.3,<2.0.0)
Requires-Dist: scikit-image (>=0.16.2,<0.17.0)
Requires-Dist: scikit-learn (>=0.22.2,<0.23.0)
Requires-Dist: scipy (>=1.4.1,<2.0.0)
Project-URL: Repository, https://github.com/mamerisawesome/gyakujinton
